{
  "data": {
    "yes_no": {
      "model": "base_dict_type",
      "properties": {
        "dictName": "是否",
        "dictType": "yes_no",
        "status": 0
      }
    },
    "yes_no_no": {
      "model": "base_dict_value",
      "properties": {
        "dictLabel": "否",
        "dictValue": "0",
        "dictType": "yes_no",
        "status": 0,
        "dictSort": 1
      }
    },
    "yes_no_yes": {
      "model": "base_dict_value",
      "properties": {
        "dictLabel": "是",
        "dictValue": "1",
        "dictType": "yes_no",
        "status": 0,
        "dictSort": 2
      }
    }
  }
}